imageSpiderByHanXu/__init__.py
imageSpiderByHanXu/baidu/__init__.py
imageSpiderByHanXu/bing/__init__.py
imageSpiderByHanXu/pixiv/__init__.py
imageSpiderByHanXu-1.0.1.dist-info/LICENSE
imageSpiderByHanXu-1.0.1.dist-info/METADATA
imageSpiderByHanXu-1.0.1.dist-info/WHEEL
imageSpiderByHanXu-1.0.1.dist-info/top_level.txt
imageSpiderByHanXu-1.0.1.dist-info/RECORD
