Metadata-Version: 2.1
Name: imageSpiderByHanXu
Version: 1.0.1
Summary: This tool allow you to crawl images from `3` website, which are Pixiv,Bing and Baidu..
Home-page: https://gitee.com/UnderTurrets/image_spider
Author: Han Xu
Author-email: 736946693@qq.com
License: UNKNOWN
Platform: UNKNOWN
Classifier: Topic :: Software Development :: Libraries :: Python Modules
Classifier: Development Status :: 4 - Beta
Classifier: License :: OSI Approved :: MIT License
Classifier: Programming Language :: Python :: 3
Classifier: Programming Language :: Python :: 3.3
Classifier: Programming Language :: Python :: 3.4
Classifier: Programming Language :: Python :: 3.5
Classifier: Programming Language :: Python :: 3.6
Classifier: Programming Language :: Python :: 3.7
Classifier: Programming Language :: Python :: 3.8
Classifier: Programming Language :: Python :: 3.9
Classifier: Operating System :: Microsoft :: Windows
Classifier: Intended Audience :: End Users/Desktop
Classifier: Natural Language :: English
Classifier: Natural Language :: Chinese (Simplified)
License-File: LICENSE
Requires-Dist: requests
Requires-Dist: tqdm
